asynces/__init__.py
asynces/connection.py
asynces/pool.py
asynces/transport.py
asynces-0.0.1.dist-info/DESCRIPTION.rst
asynces-0.0.1.dist-info/METADATA
asynces-0.0.1.dist-info/RECORD
asynces-0.0.1.dist-info/WHEEL
asynces-0.0.1.dist-info/metadata.json
asynces-0.0.1.dist-info/top_level.txt
