Metadata-Version: 2.0
Name: asynces
Version: 0.0.1
Summary: asyncio driver for elasticsearch
Home-page: https://github.com/fabregas/asynces/
Author: Kostiantyn Andrusenko
Author-email: kksstt@gmail.com
License: Apache 2
Download-URL: https://pypi.python.org/pypi/asynces
Platform: POSIX
Classifier: License :: OSI Approved :: Apache Software License
Classifier: Intended Audience :: Developers
Classifier: Programming Language :: Python :: 3.5
Classifier: Operating System :: OS Independent
Classifier: Topic :: System :: Networking
Classifier: Topic :: System :: Distributed Computing
Classifier: Development Status :: 4 - Beta
Requires-Dist: aiohttp
